[
    {
        "key": "dbln",
        "value": "%7B%2261578021825711%22%3A%22uDZCg6QW%22%7D",
        "domain": "facebook.com",
        "path": "/login/device-based/",
        "hostOnly": false,
        "creation": "2025-09-17T17:16:41.324Z",
        "lastAccessed": "2025-09-17T17:16:41.331Z"
    },
    {
        "key": "datr",
        "value": "fSnJaFGR74vmHZ3z0f6iRTVt",
        "domain": "facebook.com",
        "path": "/",
        "hostOnly": false,
        "creation": "2025-09-17T17:16:41.331Z",
        "lastAccessed": "2025-09-17T17:16:41.331Z"
    },
    {
        "key": "sb",
        "value": "fSnJaPHTWzCGVn-mUlXCVxgn",
        "domain": "facebook.com",
        "path": "/",
        "hostOnly": false,
        "creation": "2025-09-17T17:16:41.331Z",
        "lastAccessed": "2025-09-17T17:16:41.331Z"
    },
    {
        "key": "locale",
        "value": "en_GB",
        "domain": "facebook.com",
        "path": "/",
        "hostOnly": false,
        "creation": "2025-09-17T17:16:41.331Z",
        "lastAccessed": "2025-09-17T17:16:41.331Z"
    },
    {
        "key": "pas",
        "value": "61578021825711%3AsG304lXOaS",
        "domain": "facebook.com",
        "path": "/",
        "hostOnly": false,
        "creation": "2025-09-17T17:16:41.331Z",
        "lastAccessed": "2025-09-17T17:16:41.331Z"
    },
    {
        "key": "vpd",
        "value": "v1%3B754x384x1.875",
        "domain": "facebook.com",
        "path": "/",
        "hostOnly": false,
        "creation": "2025-09-17T17:16:41.331Z",
        "lastAccessed": "2025-09-17T17:16:41.331Z"
    },
    {
        "key": "ps_l",
        "value": "1",
        "domain": "facebook.com",
        "path": "/",
        "hostOnly": false,
        "creation": "2025-09-17T17:16:41.331Z",
        "lastAccessed": "2025-09-17T17:16:41.331Z"
    },
    {
        "key": "ps_n",
        "value": "1",
        "domain": "facebook.com",
        "path": "/",
        "hostOnly": false,
        "creation": "2025-09-17T17:16:41.331Z",
        "lastAccessed": "2025-09-17T17:16:41.331Z"
    },
    {
        "key": "m_pixel_ratio",
        "value": "1.875",
        "domain": "facebook.com",
        "path": "/",
        "hostOnly": false,
        "creation": "2025-09-17T17:16:41.331Z",
        "lastAccessed": "2025-09-17T17:16:41.331Z"
    },
    {
        "key": "wd",
        "value": "385x854",
        "domain": "facebook.com",
        "path": "/",
        "hostOnly": false,
        "creation": "2025-09-17T17:16:41.331Z",
        "lastAccessed": "2025-09-17T17:16:41.331Z"
    },
    {
        "key": "c_user",
        "value": "61578021825711",
        "domain": "facebook.com",
        "path": "/",
        "hostOnly": false,
        "creation": "2025-09-17T17:16:41.331Z",
        "lastAccessed": "2025-09-17T17:16:41.331Z"
    },
    {
        "key": "xs",
        "value": "22%3AtUPCgGwbNfofeg%3A2%3A1758129124%3A-1%3A-1",
        "domain": "facebook.com",
        "path": "/",
        "hostOnly": false,
        "creation": "2025-09-17T17:16:41.331Z",
        "lastAccessed": "2025-09-17T17:16:41.331Z"
    },
    {
        "key": "fr",
        "value": "0WzZ6WX9cwpEbZdcN.AWdCGJTNAwn9rNfTCRYrsj2OsJLUlVfLedwXd9AmuvGHO8gn8T4.BoySl9..AAA.0.0.Boyuvo.AWdxGPnWYuBbEQDY8gDUvOoYdAw",
        "domain": "facebook.com",
        "path": "/",
        "hostOnly": false,
        "creation": "2025-09-17T17:16:41.331Z",
        "lastAccessed": "2025-09-17T17:16:41.331Z"
    },
    {
        "key": "fbl_st",
        "value": "101739378%3BT%3A29302152",
        "domain": "facebook.com",
        "path": "/",
        "hostOnly": false,
        "creation": "2025-09-17T17:16:41.331Z",
        "lastAccessed": "2025-09-17T17:16:41.331Z"
    },
    {
        "key": "wl_cbv",
        "value": "v2%3Bclient_version%3A2926%3Btimestamp%3A1758129128",
        "domain": "facebook.com",
        "path": "/",
        "hostOnly": false,
        "creation": "2025-09-17T17:16:41.331Z",
        "lastAccessed": "2025-09-17T17:16:41.331Z"
    }
]
